ena_ons-0.1.0.dist-info/METADATA
ena_ons-0.1.0.dist-info/WHEEL
ena_ons-0.1.0.dist-info/entry_points.txt
ena_ons-0.1.0.dist-info/licenses/LICENSE
ena_ons/__init__.py
ena_ons/codigos.py
ena_ons/ena.py
ena_ons/regras.py
ena_ons-0.1.0.dist-info/RECORD
