Metadata-Version: 2.1
Name: ena-ons
Version: 0.1.0
Summary: Pacote para transformação de vazão em ENA de acordo com as regras de negócio do ONS.
Author-Email: viictor-m <magalhaes.a.victor@gmail.com>
License: MIT
Requires-Python: >=3.10
Requires-Dist: pandas>=2.2.3
Requires-Dist: pandas-stubs>=2.2.3.241126
Requires-Dist: pydantic>=2.10.6
